00_src/Smemory_single_clk.v
module Smemory_single_clk#(
    parameter SIZE_DATA  = 8,
    parameter SIZE_ADDR  = 4,
    parameter SIZE_DEPTH = 16 
)(
    input                   i_clk,
    input                   i_wr_en,
    input                   i_rd_en,
    input [SIZE_ADDR-1:0]   i_addr_wr,
    input [SIZE_ADDR-1:0]   i_addr_rd,
    input [SIZE_DATA-1:0]   i_data,
    output reg [SIZE_DATA-1:0]  o_data
);

reg [SIZE_DATA-1:0] mem [0:SIZE_DEPTH-1];

always_ff @(posedge i_clk) begin
    if(i_wr_en) begin
        mem[i_addr_wr] <= i_data;
        o_data <= 0;
    end else 
        o_data <= i_data;

    if(i_rd_en)
        o_data <= mem[i_addr_rd];
    else
        o_data <= i_data;
end

endmodule

00_src/fifo_synchronous.v
module fifo_synchronous #(
    parameter SIZE_DEPTH = 16,
    parameter SIZE_DATA  = 8
)(
    // Signal Golbal
    input                      i_clk,
    input                      i_rst_n,
    // Signal Control FIFO
    input                      i_wr_en,
    input                      i_rd_en,
    // Input FIFO
    input  [SIZE_DATA - 1:0]   i_data,
    // Output FIFO
    output reg [SIZE_DATA - 1:0]    o_data,
    // Status FIFO
    output wire                     o_full,
    output wire                     o_empty
); 

parameter SIZE_ADDR = $clog2(SIZE_DEPTH);

reg [SIZE_ADDR:0] ptr_wr, ptr_rd;
wire [SIZE_ADDR:0] n_ptr_wr, n_ptr_rd;
wire update_wr, update_rd;

assign update_wr = ~o_full & i_wr_en;
assign update_rd = ~o_empty & i_rd_en;

assign n_ptr_wr = (update_wr) ? ptr_wr + 1 : ptr_wr;
assign n_ptr_rd = (update_rd) ? ptr_rd + 1 : ptr_rd;

assign o_empty = (ptr_rd == ptr_wr) ? 1 : 0;
// assign o_full = (n_ptr_wr == ptr_rd) ? 1 : 0;
assign o_full = (~|(ptr_rd[SIZE_ADDR-1:0] ^ ptr_wr[SIZE_ADDR-1:0])) & (ptr_rd[SIZE_ADDR] ^ ptr_wr[SIZE_ADDR]);
always_ff @(posedge i_clk or negedge i_rst_n) begin 
    if(~i_rst_n) begin
        ptr_rd <= 0;
        ptr_wr <= 0;
    end else begin
        ptr_rd <= n_ptr_rd;
        ptr_wr <= n_ptr_wr; 
    end
end

Smemory_single_clk#(
    .SIZE_DATA  (SIZE_DATA),
    .SIZE_ADDR  (SIZE_ADDR),
    .SIZE_DEPTH (SIZE_DEPTH) 
) RAM (
    .i_clk          (i_clk),
    .i_wr_en        (i_wr_en),
    .i_rd_en        (i_rd_en),
    .i_addr_wr      (ptr_wr[SIZE_ADDR-1:0]),
    .i_addr_rd      (ptr_rd[SIZE_ADDR-1:0]),
    .i_data         (i_data),
    .o_data         (o_data)
);

endmodule

01_test/FIFO_synchronous/tb_fifo.v
`timescale 1ps/1ps
module tb_fifo();

  // Parameters
  parameter DATA_WIDTH = 8;
  parameter SIZE_DEPTH = 8;
  parameter ADDR_WIDTH = $clog2(SIZE_DEPTH);

  // Signals
  reg i_clk, i_rst_n;
  reg i_wr_en; // Changed to reg to drive in initial block
  reg i_rd_en; // Changed to reg to drive in initial block
  reg [DATA_WIDTH-1:0] i_data;
  reg [DATA_WIDTH-1:0] o_data;
  reg o_full, o_empty;

  // Memory to store write and read data
  reg [DATA_WIDTH-1:0] value_wr [0:SIZE_DEPTH-1];
  reg [DATA_WIDTH-1:0] value_rd [0:SIZE_DEPTH-1];
  integer count_wr, count_rd;
  integer match_count;
  // Instantiate the FIFO module

  fifo_synchronous #(
                     .SIZE_DATA(DATA_WIDTH),
                     .SIZE_DEPTH(SIZE_DEPTH)
                   ) uut (
                     .i_clk(i_clk),
                     .i_rst_n(i_rst_n),
                     .i_wr_en(i_wr_en),
                     .i_rd_en(i_rd_en),
                     .i_data(i_data),
                     .o_data(o_data),
                     .o_full(o_full),
                     .o_empty(o_empty)
                   );

always #5 i_clk = ~i_clk;

  // Dump waveform
  initial
  begin
    $dumpfile("tb_fifo.vcd");
    $dumpvars(0, tb_fifo);
  end

  // Test procedure
  initial
  begin
    // Initialize signals
    count_wr = 0;
    count_rd = 0;

    // Test case 1: Reset the FIFO
    $display("-------------- Test Case 1 --------------");
    #10;
    i_rst_n = 1;
    #10;
    @(posedge i_clk);
    i_wr_en = 1;
    i_rd_en = 0;
    i_data = 8'h29;
    
    #10;
    i_rst_n = 0;
    i_wr_en = 0;
    i_rd_en = 0;
    #10;
    $display("Test case 1: Reset the FIFO");
    $display("FIFO reset, pt_rd: %d, pt_wr: %d", uut.ptr_rd, uut.ptr_wr);
    $display("FIFO empty: %d, FIFO full: %d", o_empty, o_full);
    $display("FIFO data: %h", o_data);
    $display("=> TestCase1: %s", ((uut.ptr_rd == 0)&&(uut.ptr_wr == 0)) ? "PASS" : "FAIL");

    // Test case 2: Write data until full
    $display("-------------- Test Case 2 --------------");
    i_rst_n = 0;
    #10;
    i_rst_n = 1;
    count_wr = 0;

    repeat (SIZE_DEPTH + 1)
    begin
      @(posedge i_clk);
      i_wr_en = 1;
      i_rd_en = 0;
      i_data = $random;
      $display("Time = %t, o_full = %b, ptr_wr = %d, ptr_rd = %d",$time, o_full, uut.ptr_wr, uut.ptr_rd);
      #10;
    end
    i_wr_en = 0;

    $display("Test case 2: Write data until full");
    $display("=> TestCase2: %s", o_full ? "PASS" : "FAIL");

    // Test case 3: Read data until empty
    $display("-------------- Test Case 3 --------------");
    count_rd = 0;
    repeat (SIZE_DEPTH)
    begin
      @(posedge i_clk);
      i_wr_en = 0;
      i_rd_en = 1;
      #10;
      value_rd[count_rd] = o_data;
      count_rd = count_rd + 1;
      $display("Time = %t, o_empty = %b, ptr_wr = %d, ptr_rd = %d", $time, o_empty, uut.ptr_wr, uut.ptr_rd);
    end
    i_rd_en = 0;

    $display("Test case 3: Read data until empty");
    $display("=> TestCase3: %s", o_empty ? "PASS" : "FAIL");

    // Test case 4: Write and read simultaneously
    // Kiem tra; doc va ghi dong thoi
    $display("-------------- Test Case 4 --------------");
    #20; // reset 
    i_rst_n = 0;
    
    #20; 
    i_rst_n = 1;
    #10;

    @(posedge i_clk);
    i_wr_en = 1;
    i_rd_en = 0;
    i_data = 29;
    $display("FIFO data: i_data = %d, o_data = %d",i_data, o_data);

    @(posedge i_clk);
    i_wr_en = 1;
    i_rd_en = 1;
    i_data  = 30;
    $display("FIFO data: i_data = %d, o_data = %d",i_data, o_data);

    @(posedge i_clk);
    i_wr_en = 1;
    i_rd_en = 1;
    i_data  = 31;
    $display("FIFO data: i_data = %d, o_data = %d",i_data, o_data);
    
    @(posedge i_clk);
    i_wr_en = 1;
    i_rd_en = 1;
    i_data  = 32;
    $display("FIFO data: i_data = %d, o_data = %d",i_data, o_data);

    @(posedge i_clk);
    i_wr_en = 1;
    i_rd_en = 1;
    i_data  = 33;
    $display("FIFO data: i_data = %d, o_data = %d",i_data, o_data);

    $display("-------------- Test Case 5 --------------");
    #20 i_rst_n = 0;
    #20 i_rst_n = 1;
    #10;
    i_wr_en = 1;
    i_rd_en = 0;
    $display("Input data");
    while(!o_full) begin
        @(posedge i_clk);
        i_data = $random%(2**DATA_WIDTH);
        $display("Time=%t, i_wr_en=%b, i_rd_en=%b, i_data = %h, o_full=%b", $time, i_wr_en, i_rd_en, i_data, o_full);
    end 
    #10;
    i_wr_en = 0;
    i_rd_en = 1;
    $display("Output data");
    while(!o_empty) begin
        @(posedge i_clk);
        $display("Time=%t, i_wr_en=%b, i_rd_en=%b, o_data = %h, o_empty=%b", $time, i_wr_en, i_rd_en, o_data, o_empty);
    end

    // End simulation
    #200;
    $display("End of simulation");
    $finish;
  end

endmodule

01_test/FIFO_synchronous/tb_fifo.vcd
$version Generated by VerilatedVcd $end
$timescale 1ps $end
 $scope module TOP $end
  $scope module tb_fifo $end
   $var wire 32 E DATA_WIDTH [31:0] $end
   $var wire 32 E SIZE_DEPTH [31:0] $end
   $var wire 32 F ADDR_WIDTH [31:0] $end
   $var wire 1 @ i_clk $end
   $var wire 1 # i_rst_n $end
   $var wire 1 $ i_wr_en $end
   $var wire 1 % i_rd_en $end
   $var wire 8 & i_data [7:0] $end
   $var wire 8 1 o_data [7:0] $end
   $var wire 1 : o_full $end
   $var wire 1 ; o_empty $end
   $var wire 8 G value_wr[0] [7:0] $end
   $var wire 8 H value_wr[1] [7:0] $end
   $var wire 8 I value_wr[2] [7:0] $end
   $var wire 8 J value_wr[3] [7:0] $end
   $var wire 8 K value_wr[4] [7:0] $end
   $var wire 8 L value_wr[5] [7:0] $end
   $var wire 8 M value_wr[6] [7:0] $end
   $var wire 8 N value_wr[7] [7:0] $end
   $var wire 8 ' value_rd[0] [7:0] $end
   $var wire 8 ( value_rd[1] [7:0] $end
   $var wire 8 ) value_rd[2] [7:0] $end
   $var wire 8 * value_rd[3] [7:0] $end
   $var wire 8 + value_rd[4] [7:0] $end
   $var wire 8 , value_rd[5] [7:0] $end
   $var wire 8 - value_rd[6] [7:0] $end
   $var wire 8 . value_rd[7] [7:0] $end
   $var wire 32 / count_wr [31:0] $end
   $var wire 32 0 count_rd [31:0] $end
   $var wire 32 O match_count [31:0] $end
   $scope module uut $end
    $var wire 32 E SIZE_DEPTH [31:0] $end
    $var wire 32 E SIZE_DATA [31:0] $end
    $var wire 1 @ i_clk $end
    $var wire 1 # i_rst_n $end
    $var wire 1 $ i_wr_en $end
    $var wire 1 % i_rd_en $end
    $var wire 8 & i_data [7:0] $end
    $var wire 8 1 o_data [7:0] $end
    $var wire 1 : o_full $end
    $var wire 1 ; o_empty $end
    $var wire 32 F SIZE_ADDR [31:0] $end
    $var wire 4 < ptr_wr [3:0] $end
    $var wire 4 = ptr_rd [3:0] $end
    $var wire 4 A n_ptr_wr [3:0] $end
    $var wire 4 B n_ptr_rd [3:0] $end
    $var wire 1 C update_wr $end
    $var wire 1 D update_rd $end
    $scope module RAM $end
     $var wire 32 E SIZE_DATA [31:0] $end
     $var wire 32 F SIZE_ADDR [31:0] $end
     $var wire 32 E SIZE_DEPTH [31:0] $end
     $var wire 1 @ i_clk $end
     $var wire 1 $ i_wr_en $end
     $var wire 1 % i_rd_en $end
     $var wire 3 > i_addr_wr [2:0] $end
     $var wire 3 ? i_addr_rd [2:0] $end
     $var wire 8 & i_data [7:0] $end
     $var wire 8 1 o_data [7:0] $end
     $var wire 8 2 mem[0] [7:0] $end
     $var wire 8 3 mem[1] [7:0] $end
     $var wire 8 4 mem[2] [7:0] $end
     $var wire 8 5 mem[3] [7:0] $end
     $var wire 8 6 mem[4] [7:0] $end
     $var wire 8 7 mem[5] [7:0] $end
     $var wire 8 8 mem[6] [7:0] $end
     $var wire 8 9 mem[7] [7:0] $end
    $upscope $end
   $upscope $end
  $upscope $end
 $upscope $end
$enddefinitions $end


#0
0#
0$
0%
b00000000 &
b00000000 '
b00000000 (
b00000000 )
b00000000 *
b00000000 +
b00000000 ,
b00000000 -
b00000000 .
b00000000000000000000000000000000 /
b00000000000000000000000000000000 0
b00000000 1
b00000000 2
b00000000 3
b00000000 4
b00000000 5
b00000000 6
b00000000 7
b00000000 8
b00000000 9
0:
1;
b0000 <
b0000 =
b000 >
b000 ?
0@
b0000 A
b0000 B
0C
0D
b00000000000000000000000000001000 E
b00000000000000000000000000000011 F
b00000000 G
b00000000 H
b00000000 I
b00000000 J
b00000000 K
b00000000 L
b00000000 M
b00000000 N
b00000000000000000000000000000000 O
#5
1@
#10
1#
0@
#15
1@
#20
0@
#25
1$
b00101001 &
b00101001 1
b00101001 2
0;
b0001 <
b001 >
1@
b0010 A
1C
#30
0@
#35
0#
0$
1;
b0000 <
b000 >
1@
b0000 A
0C
#40
0@
#45
1@
#50
0@
#55
1#
1@
#60
0@
#65
1$
b11000100 &
b11000100 1
b11000100 2
0;
b0001 <
b001 >
1@
b0010 A
1C
#70
0@
#75
b11000100 3
b0010 <
b010 >
1@
b0011 A
#80
0@
#85
b10011100 &
b10011100 1
b10011100 4
b0011 <
b011 >
1@
b0100 A
#90
0@
#95
b10011100 5
b0100 <
b100 >
1@
b0101 A
#100
0@
#105
b00000010 &
b00000010 1
b00000010 6
b0101 <
b101 >
1@
b0110 A
#110
0@
#115
b00000010 7
b0110 <
b110 >
1@
b0111 A
#120
0@
#125
b11100100 &
b11100100 1
b11100100 8
b0111 <
b111 >
1@
b1000 A
#130
0@
#135
b11100100 9
1:
b1000 <
b000 >
1@
0C
#140
0@
#145
b01111000 &
b01111000 1
b01111000 2
1@
#150
0@
#155
1@
#160
0@
#165
b10111100 &
b10111100 1
b10111100 2
1@
#170
0@
#175
1@
#180
0@
#185
b10110110 &
b10110110 1
b10110110 2
1@
#190
0@
#195
1@
#200
0@
#205
b11100100 &
b11100100 1
b11100100 2
1@
#210
0@
#215
1@
#220
0@
#225
b10110111 &
b10110111 1
b10110111 2
1@
#230
0@
#235
0$
1@
#240
0@
#245
1%
0:
b0001 =
b001 ?
1@
b0010 B
1D
#250
0@
#255
b10110111 '
b00000000000000000000000000000001 0
b11000100 1
b0010 =
b010 ?
1@
b0011 B
#260
0@
#265
b10011100 1
b0011 =
b011 ?
1@
b0100 B
#270
0@
#275
b10011100 (
b00000000000000000000000000000010 0
b0100 =
b100 ?
1@
b0101 B
#280
0@
#285
b00000010 1
b0101 =
b101 ?
1@
b0110 B
#290
0@
#295
b00000010 )
b00000000000000000000000000000011 0
b0110 =
b110 ?
1@
b0111 B
#300
0@
#305
b11100100 1
b0111 =
b111 ?
1@
b1000 B
#310
0@
#315
b11100100 *
b00000000000000000000000000000100 0
1;
b1000 =
b000 ?
1@
0D
#320
0@
#325
b10110111 1
1@
#330
0@
#335
b10110111 +
b00000000000000000000000000000101 0
1@
#340
0@
#345
1@
#350
0@
#355
b10110111 ,
b00000000000000000000000000000110 0
1@
#360
0@
#365
1@
#370
0@
#375
b10110111 -
b00000000000000000000000000000111 0
1@
#380
0@
#385
1@
#390
0@
#395
0%
b10110111 .
b00000000000000000000000000001000 0
1@
#400
0@
#405
1@
#410
0@
#415
0#
b0000 <
b0000 =
1@
b0000 A
b0000 B
#420
0@
#425
1@
#430
0@
#435
1#
1@
#440
0@
#445
1@
#450
0@
#455
1$
b00011101 &
b00011101 1
b00011101 2
0;
b0001 <
b001 >
1@
b0010 A
1C
#460
0@
#465
1%
b00011110 &
b00011110 3
b0010 <
b0001 =
b010 >
b001 ?
1@
b0011 A
b0010 B
1D
#470
0@
#475
b00011111 &
b00011110 1
b00011111 4
b0011 <
b0010 =
b011 >
b010 ?
1@
b0100 A
b0011 B
#480
0@
#485
b00100000 &
b00011111 1
b00100000 5
b0100 <
b0011 =
b100 >
b011 ?
1@
b0101 A
b0100 B
#490
0@
#495
b00100001 &
b00100000 1
b00100001 6
b0101 <
b0100 =
b101 >
b100 ?
1@
b0110 A
b0101 B
#500
0@
#505
b00100001 1
b00100001 7
b0110 <
b0101 =
b110 >
b101 ?
1@
b0111 A
b0110 B
#510
0@
#515
0#
b00100001 8
1;
b0000 <
b0000 =
b000 >
b000 ?
1@
b0001 A
b0000 B
0D
#520
0@
#525
b00011101 1
b00100001 2
1@
#530
0@
#535
1#
b00100001 1
0;
b0001 <
b001 >
1@
b0010 A
b0001 B
1D
#540
0@
#545
0%
b00100001 3
b0010 <
b010 >
1@
b0011 A
b0000 B
0D
#550
0@
#555
b01010011 &
b01010011 1
b01010011 4
b0011 <
b011 >
1@
b0100 A
#560
0@
#565
b00100001 &
b00100001 1
b00100001 5
b0100 <
b100 >
1@
b0101 A
#570
0@
#575
b11100001 &
b11100001 1
b11100001 6
b0101 <
b101 >
1@
b0110 A
#580
0@
#585
b11000101 &
b11000101 1
b11000101 7
b0110 <
b110 >
1@
b0111 A
#590
0@
#595
b10000010 &
b10000010 1
b10000010 8
b0111 <
b111 >
1@
b1000 A
#600
0@
#605
b01100010 &
b01100010 1
b01100010 9
1:
b1000 <
b000 >
1@
0C
#610
0@
#615
b00110101 &
b00110101 1
b00110101 2
1@
#620
0@
#625
0$
1%
0:
b0001 =
b001 ?
1@
b0010 B
1D
#630
0@
#635
b00100001 1
b0010 =
b010 ?
1@
b0011 B
#640
0@
#645
b01010011 1
b0011 =
b011 ?
1@
b0100 B
#650
0@
#655
b00100001 1
b0100 =
b100 ?
1@
b0101 B
#660
0@
#665
b11100001 1
b0101 =
b101 ?
1@
b0110 B
#670
0@
#675
b11000101 1
b0110 =
b110 ?
1@
b0111 B
#680
0@
#685
b10000010 1
b0111 =
b111 ?
1@
b1000 B
#690
0@
#695
b01100010 1
1;
b1000 =
b000 ?
1@
0D
#700
0@
#705
b00110101 1
1@
