00_src/Smemory_single_clk.v
module Smemory_single_clk#(
    parameter SIZE_DATA  = 8,
    parameter SIZE_ADDR  = 4,
    parameter SIZE_DEPTH = 16 
)(
    input                   i_clk,
    input                   i_wr_en,
    input                   i_rd_en,
    input [SIZE_ADDR-1:0]   i_addr_wr,
    input [SIZE_ADDR-1:0]   i_addr_rd,
    input [SIZE_DATA-1:0]   i_data,
    output reg [SIZE_DATA-1:0]  o_data
);

reg [SIZE_DATA-1:0] mem [0:SIZE_DEPTH-1];

always_ff @(posedge i_clk) begin
    if(i_wr_en) begin
        mem[i_addr_wr] <= i_data;
        o_data <= 0;
    end else 
        o_data <= i_data;

    if(i_rd_en)
        o_data <= mem[i_addr_rd];
    else
        o_data <= i_data;
end

endmodule

00_src/fifo_synchronous.v
module fifo_synchronous #(
    parameter SIZE_DEPTH = 16,
    parameter SIZE_DATA  = 8
)(
    // Signal Golbal
    input                      i_clk,
    input                      i_rst_n,
    // Signal Control FIFO
    input                      i_wr_en,
    input                      i_rd_en,
    // Input FIFO
    input  [SIZE_DATA - 1:0]   i_data,
    // Output FIFO
    output reg [SIZE_DATA - 1:0]    o_data,
    // Status FIFO
    output wire                     o_full,
    output wire                     o_empty
); 

parameter SIZE_ADDR = $clog2(SIZE_DEPTH);

reg [SIZE_ADDR:0] ptr_wr, ptr_rd;
wire [SIZE_ADDR:0] n_ptr_wr, n_ptr_rd;
wire update_wr, update_rd;

assign update_wr = ~o_full & i_wr_en;
assign update_rd = ~o_empty & i_rd_en;

assign n_ptr_wr = (update_wr) ? ptr_wr + 1 : ptr_wr;
assign n_ptr_rd = (update_rd) ? ptr_rd + 1 : ptr_rd;

assign o_empty = (ptr_rd == ptr_wr) ? 1 : 0;
// assign o_full = (n_ptr_wr == ptr_rd) ? 1 : 0;
assign o_full = (ptr_rd[SIZE_ADDR-1:0] == ptr_wr[SIZE_ADDR-1:0]) && (ptr_rd[SIZE_ADDR] != ptr_wr[SIZE_ADDR]);
always_ff @(posedge i_clk or negedge i_rst_n) begin 
    if(~i_rst_n) begin
        ptr_rd <= 0;
        ptr_wr <= 0;
    end else begin
        ptr_rd <= n_ptr_rd;
        ptr_wr <= n_ptr_wr; 
    end
end

Smemory_single_clk#(
    .SIZE_DATA  (SIZE_DATA),
    .SIZE_ADDR  (SIZE_ADDR),
    .SIZE_DEPTH (SIZE_DEPTH) 
) RAM (
    .i_clk          (i_clk),
    .i_wr_en        (i_wr_en),
    .i_rd_en        (i_rd_en),
    .i_addr_wr      (ptr_wr[SIZE_ADDR-1:0]),
    .i_addr_rd      (ptr_rd[SIZE_ADDR-1:0]),
    .i_data         (i_data),
    .o_data         (o_data)
);

endmodule

01_test/tb_fifo.v
`timescale 1ps/1ps
module tb_fifo();

  // Parameters
  parameter DATA_WIDTH = 8;
  parameter SIZE_DEPTH = 16;
  parameter ADDR_WIDTH = $clog2(SIZE_DEPTH);

  // Signals
  reg i_clk, i_rst_n;
  reg i_wr_en; // Changed to reg to drive in initial block
  reg i_rd_en; // Changed to reg to drive in initial block
  reg [DATA_WIDTH-1:0] i_data;
  reg [DATA_WIDTH-1:0] o_data;
  reg o_full, o_empty;

  // Memory to store write and read data
  reg [DATA_WIDTH-1:0] value_wr [0:SIZE_DEPTH-1];
  reg [DATA_WIDTH-1:0] value_rd [0:SIZE_DEPTH-1];
  integer count_wr, count_rd;
  integer match_count;
  // Instantiate the FIFO module

  fifo_synchronous #(
                     .SIZE_DATA(DATA_WIDTH),
                     .SIZE_DEPTH(SIZE_DEPTH)
                   ) uut (
                     .i_clk(i_clk),
                     .i_rst_n(i_rst_n),
                     .i_wr_en(i_wr_en),
                     .i_rd_en(i_rd_en),
                     .i_data(i_data),
                     .o_data(o_data),
                     .o_full(o_full),
                     .o_empty(o_empty)
                   );

always #5 i_clk = ~i_clk;

  // Dump waveform
  initial
  begin
    $dumpfile("tb_fifo.vcd");
    $dumpvars(0, tb_fifo);
  end

  // Test procedure
  initial
  begin
    // Initialize signals
    count_wr = 0;
    count_rd = 0;

    // Test case 1: Reset the FIFO
    $display("-------------- Test Case 1 --------------");
    #10;
    i_rst_n = 1;
    #10;
    @(posedge i_clk);
    i_wr_en = 1;
    i_rd_en = 0;
    i_data = 8'h29;
    
    #10;
    i_rst_n = 0;
    i_wr_en = 0;
    i_rd_en = 0;
    #10;
    $display("Test case 1: Reset the FIFO");
    $display("FIFO reset, pt_rd: %d, pt_wr: %d", uut.ptr_rd, uut.ptr_wr);
    $display("FIFO empty: %d, FIFO full: %d", o_empty, o_full);
    $display("FIFO data: %h", o_data);
    $display("=> TestCase1: %s", ((uut.ptr_rd == 0)&&(uut.ptr_wr == 0)) ? "PASS" : "FAIL");

    // Test case 2: Write data until full
    $display("-------------- Test Case 2 --------------");
    i_rst_n = 0;
    #10;
    i_rst_n = 1;
    count_wr = 0;

    repeat (SIZE_DEPTH + 1)
    begin
      @(posedge i_clk);
      i_wr_en = 1;
      i_rd_en = 0;
      i_data = $random;
      $display("Time = %t, o_full = %b, ptr_wr = %d, ptr_rd = %d",$time, o_full, uut.ptr_wr, uut.ptr_rd);
      #10;
    end
    i_wr_en = 0;

    $display("Test case 2: Write data until full");
    $display("=> TestCase2: %s", o_full ? "PASS" : "FAIL");

    // Test case 3: Read data until empty
    $display("-------------- Test Case 3 --------------");
    count_rd = 0;
    repeat (SIZE_DEPTH)
    begin
      @(posedge i_clk);
      i_wr_en = 0;
      i_rd_en = 1;
      #10;
      value_rd[count_rd] = o_data;
      count_rd = count_rd + 1;
      $display("Time = %t, o_empty = %b, ptr_wr = %d, ptr_rd = %d", $time, o_empty, uut.ptr_wr, uut.ptr_rd);
    end
    i_rd_en = 0;

    $display("Test case 3: Read data until empty");
    $display("=> TestCase3: %s", o_empty ? "PASS" : "FAIL");

    // Test case 4: Write and read simultaneously
    // Kiem tra; doc va ghi dong thoi
    $display("-------------- Test Case 4 --------------");
    #20; // reset 
    i_rst_n = 0;
    
    #20; 
    i_rst_n = 1;
    #10;

    @(posedge i_clk);
    i_wr_en = 1;
    i_rd_en = 0;
    i_data = 29;
    $display("FIFO data: i_data = %d, o_data = %d",i_data, o_data);

    @(posedge i_clk);
    i_wr_en = 1;
    i_rd_en = 1;
    i_data  = 30;
    $display("FIFO data: i_data = %d, o_data = %d",i_data, o_data);

    @(posedge i_clk);
    i_wr_en = 1;
    i_rd_en = 1;
    i_data  = 31;
    $display("FIFO data: i_data = %d, o_data = %d",i_data, o_data);
    
    @(posedge i_clk);
    i_wr_en = 1;
    i_rd_en = 1;
    i_data  = 32;
    $display("FIFO data: i_data = %d, o_data = %d",i_data, o_data);

    @(posedge i_clk);
    i_wr_en = 1;
    i_rd_en = 1;
    i_data  = 33;
    $display("FIFO data: i_data = %d, o_data = %d",i_data, o_data);

    $display("-------------- Test Case 5 --------------");
    // Test case 5: Write data when full

    

    // // Test case 6: Write data when full
    // @(posedge i_clk);
    // i_wr_en = 1;
    // i_rd_en = 0;
    // i_data = $random;
    // #10;
    // i_wr_en = 0;

    // $display("Test case 6: Write data when full");
    // $display("=> TestCase6: %s", o_full ? "PASS" : "FAIL");

    // // Test case 7: Read data when empty
    // i_rst_n = 0;
    // #10;
    // i_rst_n = 1;
    // @(posedge i_clk);
    // i_wr_en = 0;
    // i_rd_en = 1;
    // #10;
    // i_rd_en = 0;

    // $display("Test case 7: Read data when empty");
    // $display("=> TestCase7: %s", o_empty ? "PASS" : "FAIL");

    // End simulation
    #200;
    $display("End of simulation");
    $finish;
  end

endmodule




// `timescale 1ns/1ps
// module tb_fifo();

// reg           clk;
// reg           rst_n;
// reg           i_wr_en;
// reg           i_rd_en;
// reg  [15:0]   i_data;     // Giả định SIZE_DATA = 16
// wire [15:0]   o_data;
// wire          o_full;
// wire          o_empty;

// reg  [15:0]   rdata;
// reg           stop;

// // Instantiate DUT
// fifo_synchronous #(
//   .SIZE_DEPTH(8),
//   .SIZE_DATA(16)
// ) u_fifo (
//   .i_clk     (clk),
//   .i_rst_n   (rst_n),
//   .i_wr_en   (i_wr_en),
//   .i_rd_en   (i_rd_en),
//   .i_data    (i_data),
//   .o_data    (o_data),
//   .o_full    (o_full),
//   .o_empty   (o_empty)
// );

// // Clock generation
// always #10 clk = ~clk;

//   initial
//   begin
//     $dumpfile("tb_fifo.vcd");
//     $dumpvars(0, tb_fifo);
//   end
// // Reset and stimulus init
// initial begin
//   clk      = 0;
//   rst_n    = 0;
//   i_wr_en  = 0;
//   i_rd_en  = 0;
//   stop     = 0;
//   i_data   = 0;

//   #50 rst_n = 1;
// end

// // Write process
// initial begin
//   @(posedge clk);

//   for (int i = 0; i < 20; i++) begin
//     // Wait until FIFO has space
//     while (o_full) begin
//       @(posedge clk);
//       $display("[%0t] FIFO FULL, waiting...", $time);
//     end

//     i_wr_en <= $random;
//     i_data  <= $random;

//     $display("[%0t] WRITE: i=%0d wr_en=%0d data=0x%0h", $time, i, i_wr_en, i_data);
//     @(posedge clk);
//   end

//   i_wr_en <= 0;
//   stop <= 1;
// end

// // Read process
// initial begin
//   @(posedge clk);

//   while (!stop) begin
//     while (o_empty) begin
//       i_rd_en <= 0;
//       $display("[%0t] FIFO EMPTY, waiting...", $time);
//       @(posedge clk);
//     end

//     i_rd_en <= $random;
//     @(posedge clk);
//     rdata <= o_data;
//     $display("[%0t] READ: rd_en=%0d data=0x%0h", $time, i_rd_en, rdata);
//   end

//   i_rd_en <= 0;
//   #500 $finish;
// end

// endmodule

01_test/tb_fifo.vcd
$version Generated by VerilatedVcd $end
$timescale 1ps $end
 $scope module TOP $end
  $scope module tb_fifo $end
   $var wire 32 U DATA_WIDTH [31:0] $end
   $var wire 32 V SIZE_DEPTH [31:0] $end
   $var wire 32 W ADDR_WIDTH [31:0] $end
   $var wire 1 P i_clk $end
   $var wire 1 # i_rst_n $end
   $var wire 1 $ i_wr_en $end
   $var wire 1 % i_rd_en $end
   $var wire 8 & i_data [7:0] $end
   $var wire 8 9 o_data [7:0] $end
   $var wire 1 J o_full $end
   $var wire 1 K o_empty $end
   $var wire 8 X value_wr[0] [7:0] $end
   $var wire 8 Y value_wr[1] [7:0] $end
   $var wire 8 Z value_wr[2] [7:0] $end
   $var wire 8 [ value_wr[3] [7:0] $end
   $var wire 8 \ value_wr[4] [7:0] $end
   $var wire 8 ] value_wr[5] [7:0] $end
   $var wire 8 ^ value_wr[6] [7:0] $end
   $var wire 8 _ value_wr[7] [7:0] $end
   $var wire 8 ` value_wr[8] [7:0] $end
   $var wire 8 a value_wr[9] [7:0] $end
   $var wire 8 b value_wr[10] [7:0] $end
   $var wire 8 c value_wr[11] [7:0] $end
   $var wire 8 d value_wr[12] [7:0] $end
   $var wire 8 e value_wr[13] [7:0] $end
   $var wire 8 f value_wr[14] [7:0] $end
   $var wire 8 g value_wr[15] [7:0] $end
   $var wire 8 ' value_rd[0] [7:0] $end
   $var wire 8 ( value_rd[1] [7:0] $end
   $var wire 8 ) value_rd[2] [7:0] $end
   $var wire 8 * value_rd[3] [7:0] $end
   $var wire 8 + value_rd[4] [7:0] $end
   $var wire 8 , value_rd[5] [7:0] $end
   $var wire 8 - value_rd[6] [7:0] $end
   $var wire 8 . value_rd[7] [7:0] $end
   $var wire 8 / value_rd[8] [7:0] $end
   $var wire 8 0 value_rd[9] [7:0] $end
   $var wire 8 1 value_rd[10] [7:0] $end
   $var wire 8 2 value_rd[11] [7:0] $end
   $var wire 8 3 value_rd[12] [7:0] $end
   $var wire 8 4 value_rd[13] [7:0] $end
   $var wire 8 5 value_rd[14] [7:0] $end
   $var wire 8 6 value_rd[15] [7:0] $end
   $var wire 32 7 count_wr [31:0] $end
   $var wire 32 8 count_rd [31:0] $end
   $var wire 32 h match_count [31:0] $end
   $scope module uut $end
    $var wire 32 V SIZE_DEPTH [31:0] $end
    $var wire 32 U SIZE_DATA [31:0] $end
    $var wire 1 P i_clk $end
    $var wire 1 # i_rst_n $end
    $var wire 1 $ i_wr_en $end
    $var wire 1 % i_rd_en $end
    $var wire 8 & i_data [7:0] $end
    $var wire 8 9 o_data [7:0] $end
    $var wire 1 J o_full $end
    $var wire 1 K o_empty $end
    $var wire 32 W SIZE_ADDR [31:0] $end
    $var wire 5 L ptr_wr [4:0] $end
    $var wire 5 M ptr_rd [4:0] $end
    $var wire 5 Q n_ptr_wr [4:0] $end
    $var wire 5 R n_ptr_rd [4:0] $end
    $var wire 1 S update_wr $end
    $var wire 1 T update_rd $end
    $scope module RAM $end
     $var wire 32 U SIZE_DATA [31:0] $end
     $var wire 32 W SIZE_ADDR [31:0] $end
     $var wire 32 V SIZE_DEPTH [31:0] $end
     $var wire 1 P i_clk $end
     $var wire 1 $ i_wr_en $end
     $var wire 1 % i_rd_en $end
     $var wire 4 N i_addr_wr [3:0] $end
     $var wire 4 O i_addr_rd [3:0] $end
     $var wire 8 & i_data [7:0] $end
     $var wire 8 9 o_data [7:0] $end
     $var wire 8 : mem[0] [7:0] $end
     $var wire 8 ; mem[1] [7:0] $end
     $var wire 8 < mem[2] [7:0] $end
     $var wire 8 = mem[3] [7:0] $end
     $var wire 8 > mem[4] [7:0] $end
     $var wire 8 ? mem[5] [7:0] $end
     $var wire 8 @ mem[6] [7:0] $end
     $var wire 8 A mem[7] [7:0] $end
     $var wire 8 B mem[8] [7:0] $end
     $var wire 8 C mem[9] [7:0] $end
     $var wire 8 D mem[10] [7:0] $end
     $var wire 8 E mem[11] [7:0] $end
     $var wire 8 F mem[12] [7:0] $end
     $var wire 8 G mem[13] [7:0] $end
     $var wire 8 H mem[14] [7:0] $end
     $var wire 8 I mem[15] [7:0] $end
    $upscope $end
   $upscope $end
  $upscope $end
 $upscope $end
$enddefinitions $end


#0
0#
0$
0%
b00000000 &
b00000000 '
b00000000 (
b00000000 )
b00000000 *
b00000000 +
b00000000 ,
b00000000 -
b00000000 .
b00000000 /
b00000000 0
b00000000 1
b00000000 2
b00000000 3
b00000000 4
b00000000 5
b00000000 6
b00000000000000000000000000000000 7
b00000000000000000000000000000000 8
b00000000 9
b00000000 :
b00000000 ;
b00000000 <
b00000000 =
b00000000 >
b00000000 ?
b00000000 @
b00000000 A
b00000000 B
b00000000 C
b00000000 D
b00000000 E
b00000000 F
b00000000 G
b00000000 H
b00000000 I
0J
1K
b00000 L
b00000 M
b0000 N
b0000 O
0P
b00000 Q
b00000 R
0S
0T
b00000000000000000000000000001000 U
b00000000000000000000000000010000 V
b00000000000000000000000000000100 W
b00000000 X
b00000000 Y
b00000000 Z
b00000000 [
b00000000 \
b00000000 ]
b00000000 ^
b00000000 _
b00000000 `
b00000000 a
b00000000 b
b00000000 c
b00000000 d
b00000000 e
b00000000 f
b00000000 g
b00000000000000000000000000000000 h
#5
1P
#10
1#
0P
#15
1P
#20
0P
#25
1$
b00101001 &
b00101001 9
b00101001 :
0K
b00001 L
b0001 N
1P
b00010 Q
1S
#30
0P
#35
0#
0$
1K
b00000 L
b0000 N
1P
b00000 Q
0S
#40
0P
#45
1P
#50
0P
#55
1#
1P
#60
0P
#65
1$
b11000100 &
b11000100 9
b11000100 :
0K
b00001 L
b0001 N
1P
b00010 Q
1S
#70
0P
#75
b11000100 ;
b00010 L
b0010 N
1P
b00011 Q
#80
0P
#85
b10011100 &
b10011100 9
b10011100 <
b00011 L
b0011 N
1P
b00100 Q
#90
0P
#95
b10011100 =
b00100 L
b0100 N
1P
b00101 Q
#100
0P
#105
b00000010 &
b00000010 9
b00000010 >
b00101 L
b0101 N
1P
b00110 Q
#110
0P
#115
b00000010 ?
b00110 L
b0110 N
1P
b00111 Q
#120
0P
#125
b11100100 &
b11100100 9
b11100100 @
b00111 L
b0111 N
1P
b01000 Q
#130
0P
#135
b11100100 A
b01000 L
b1000 N
1P
b01001 Q
#140
0P
#145
b01111000 &
b01111000 9
b01111000 B
b01001 L
b1001 N
1P
b01010 Q
#150
0P
#155
b01111000 C
b01010 L
b1010 N
1P
b01011 Q
#160
0P
#165
b10111100 &
b10111100 9
b10111100 D
b01011 L
b1011 N
1P
b01100 Q
#170
0P
#175
b10111100 E
b01100 L
b1100 N
1P
b01101 Q
#180
0P
#185
b10110110 &
b10110110 9
b10110110 F
b01101 L
b1101 N
1P
b01110 Q
#190
0P
#195
b10110110 G
b01110 L
b1110 N
1P
b01111 Q
#200
0P
#205
b11100100 &
b11100100 9
b11100100 H
b01111 L
b1111 N
1P
b10000 Q
#210
0P
#215
b11100100 I
1J
b10000 L
b0000 N
1P
0S
#220
0P
#225
b10110111 &
b10110111 9
b10110111 :
1P
#230
0P
#235
1P
#240
0P
#245
b01010011 &
b01010011 9
b01010011 :
1P
#250
0P
#255
1P
#260
0P
#265
b00100001 &
b00100001 9
b00100001 :
1P
#270
0P
#275
1P
#280
0P
#285
b11100001 &
b11100001 9
b11100001 :
1P
#290
0P
#295
1P
#300
0P
#305
b11000101 &
b11000101 9
b11000101 :
1P
#310
0P
#315
1P
#320
0P
#325
b10000010 &
b10000010 9
b10000010 :
1P
#330
0P
#335
1P
#340
0P
#345
b01100010 &
b01100010 9
b01100010 :
1P
#350
0P
#355
1P
#360
0P
#365
b00110101 &
b00110101 9
b00110101 :
1P
#370
0P
#375
1P
#380
0P
#385
b00010010 &
b00010010 9
b00010010 :
1P
#390
0P
#395
0$
1P
#400
0P
#405
1%
0J
b00001 M
b0001 O
1P
b00010 R
1T
#410
0P
#415
b00010010 '
b00000000000000000000000000000001 8
b11000100 9
b00010 M
b0010 O
1P
b00011 R
#420
0P
#425
b10011100 9
b00011 M
b0011 O
1P
b00100 R
#430
0P
#435
b10011100 (
b00000000000000000000000000000010 8
b00100 M
b0100 O
1P
b00101 R
#440
0P
#445
b00000010 9
b00101 M
b0101 O
1P
b00110 R
#450
0P
#455
b00000010 )
b00000000000000000000000000000011 8
b00110 M
b0110 O
1P
b00111 R
#460
0P
#465
b11100100 9
b00111 M
b0111 O
1P
b01000 R
#470
0P
#475
b11100100 *
b00000000000000000000000000000100 8
b01000 M
b1000 O
1P
b01001 R
#480
0P
#485
b01111000 9
b01001 M
b1001 O
1P
b01010 R
#490
0P
#495
b01111000 +
b00000000000000000000000000000101 8
b01010 M
b1010 O
1P
b01011 R
#500
0P
#505
b10111100 9
b01011 M
b1011 O
1P
b01100 R
#510
0P
#515
b10111100 ,
b00000000000000000000000000000110 8
b01100 M
b1100 O
1P
b01101 R
#520
0P
#525
b10110110 9
b01101 M
b1101 O
1P
b01110 R
#530
0P
#535
b10110110 -
b00000000000000000000000000000111 8
b01110 M
b1110 O
1P
b01111 R
#540
0P
#545
b11100100 9
b01111 M
b1111 O
1P
b10000 R
#550
0P
#555
b11100100 .
b00000000000000000000000000001000 8
1K
b10000 M
b0000 O
1P
0T
#560
0P
#565
b00010010 9
1P
#570
0P
#575
b00010010 /
b00000000000000000000000000001001 8
1P
#580
0P
#585
1P
#590
0P
#595
b00010010 0
b00000000000000000000000000001010 8
1P
#600
0P
#605
1P
#610
0P
#615
b00010010 1
b00000000000000000000000000001011 8
1P
#620
0P
#625
1P
#630
0P
#635
b00010010 2
b00000000000000000000000000001100 8
1P
#640
0P
#645
1P
#650
0P
#655
b00010010 3
b00000000000000000000000000001101 8
1P
#660
0P
#665
1P
#670
0P
#675
b00010010 4
b00000000000000000000000000001110 8
1P
#680
0P
#685
1P
#690
0P
#695
b00010010 5
b00000000000000000000000000001111 8
1P
#700
0P
#705
1P
#710
0P
#715
0%
b00010010 6
b00000000000000000000000000010000 8
1P
#720
0P
#725
1P
#730
0P
#735
0#
b00000 L
b00000 M
1P
b00000 Q
b00000 R
#740
0P
#745
1P
#750
0P
#755
1#
1P
#760
0P
#765
1P
#770
0P
#775
1$
b00011101 &
b00011101 9
b00011101 :
0K
b00001 L
b0001 N
1P
b00010 Q
1S
#780
0P
#785
1%
b00011110 &
b00011110 ;
b00010 L
b00001 M
b0010 N
b0001 O
1P
b00011 Q
b00010 R
1T
#790
0P
#795
b00011111 &
b00011110 9
b00011111 <
b00011 L
b00010 M
b0011 N
b0010 O
1P
b00100 Q
b00011 R
#800
0P
#805
b00100000 &
b00011111 9
b00100000 =
b00100 L
b00011 M
b0100 N
b0011 O
1P
b00101 Q
b00100 R
#810
0P
#815
b00100001 &
b00100000 9
b00100001 >
b00101 L
b00100 M
b0101 N
b0100 O
1P
b00110 Q
b00101 R
#820
0P
#825
b00100001 9
b00100001 ?
b00110 L
b00101 M
b0110 N
b0101 O
1P
b00111 Q
b00110 R
#830
0P
#835
b00100001 @
b00111 L
b00110 M
b0111 N
b0110 O
1P
b01000 Q
b00111 R
#840
0P
#845
b00100001 A
b01000 L
b00111 M
b1000 N
b0111 O
1P
b01001 Q
b01000 R
#850
0P
#855
b00100001 B
b01001 L
b01000 M
b1001 N
b1000 O
1P
b01010 Q
b01001 R
#860
0P
#865
b00100001 C
b01010 L
b01001 M
b1010 N
b1001 O
1P
b01011 Q
b01010 R
#870
0P
#875
b00100001 D
b01011 L
b01010 M
b1011 N
b1010 O
1P
b01100 Q
b01011 R
#880
0P
#885
b00100001 E
b01100 L
b01011 M
b1100 N
b1011 O
1P
b01101 Q
b01100 R
#890
0P
#895
b00100001 F
b01101 L
b01100 M
b1101 N
b1100 O
1P
b01110 Q
b01101 R
#900
0P
#905
b00100001 G
b01110 L
b01101 M
b1110 N
b1101 O
1P
b01111 Q
b01110 R
#910
0P
#915
b00100001 H
b01111 L
b01110 M
b1111 N
b1110 O
1P
b10000 Q
b01111 R
#920
0P
#925
b00100001 I
b10000 L
b01111 M
b0000 N
b1111 O
1P
b10001 Q
b10000 R
#930
0P
#935
b00100001 :
b10001 L
b10000 M
b0001 N
b0000 O
1P
b10010 Q
b10001 R
#940
0P
#945
b00100001 ;
b10010 L
b10001 M
b0010 N
b0001 O
1P
b10011 Q
b10010 R
#950
0P
#955
b00100001 <
b10011 L
b10010 M
b0011 N
b0010 O
1P
b10100 Q
b10011 R
#960
0P
#965
b00100001 =
b10100 L
b10011 M
b0100 N
b0011 O
1P
b10101 Q
b10100 R
#970
0P
#975
b10101 L
b10100 M
b0101 N
b0100 O
1P
b10110 Q
b10101 R
#980
0P
#985
b10110 L
b10101 M
b0110 N
b0101 O
1P
b10111 Q
b10110 R
#990
0P
#995
b10111 L
b10110 M
b0111 N
b0110 O
1P
b11000 Q
b10111 R
#1000
0P
#1005
b11000 L
b10111 M
b1000 N
b0111 O
1P
b11001 Q
b11000 R
#1010
0P
#1015
b11001 L
b11000 M
b1001 N
b1000 O
1P
b11010 Q
b11001 R
