00_src/LUT.v
module LUT#(
    parameter SIZE_DATA = 8,
    parameter SIZE_ADDR = 3
)(
    input               i_clk,
    input               i_rst_n,
    input               i_wr_en,
    input               i_rd_en,
    input [SIZE_ADDR - 1: 0] i_wr_addr,
    input [SIZE_ADDR - 1: 0] i_rd_addr,
    input [SIZE_DATA - 1: 0]    i_data,
    output reg [SIZE_DATA - 1: 0] o_data
);

reg [SIZE_DATA - 1:0] mem [0 :SIZE_ADDR - 1];

always @(posedge i_clk or negedge i_rst_n) begin
    if(~i_rst_n) begin
        mem[0]    <= 0;
        o_data    <= 0;
    end else begin 
        if(i_wr_en) 
            mem[i_wr_addr] <= i_data;
        else if(i_rd_en)
            o_data <= mem[i_rd_addr];
    end 
end 

endmodule

00_src/fifo_synchronous.v
module fifo_synchronous #(
    parameter SIZE_DEPTH = 8,
    parameter SIZE_DATA = 8
)(
    // Signal Golbal
    input                      i_clk,
    input                      i_rst_n,
    // Signal Control FIFO
    input                      i_wr_en,
    input                      i_rd_en,
    // Input FIFO
    input  [SIZE_DATA - 1:0]   i_data,
    // Output FIFO
    output reg [SIZE_DATA - 1:0]  o_data,
    // Status FIFO
    output wire                    o_full,
    output wire                    o_empty
);  

parameter ADDR = $clog2(SIZE_DEPTH);
reg [ADDR - 1: 0] ptr_rd, ptr_wr;
reg [ADDR - 1: 0] n_ptr_rd, n_ptr_wr;

// Status FIFO
assign o_full = (~|(ptr_rd ^ n_ptr_wr));
assign o_empty = (~|(ptr_rd ^ ptr_wr));


LUT #(
    .SIZE_DATA(SIZE_DATA),
    .SIZE_ADDR(ADDR)
)lut_mem(
    .i_clk (i_clk),
    .i_rst_n(i_rst_n),
    .i_wr_en(i_wr_en),
    .i_rd_en(i_rd_en),
    .i_wr_addr(ptr_wr),
    .i_rd_addr(ptr_rd),
    .i_data(i_data),

    .o_data(o_data)
);

always_comb begin
    if((~o_full) && (ptr_wr == ADDR - 2) && (i_wr_en))
        n_ptr_wr = 0;
    else if((~o_full)&&(i_wr_en))
        n_ptr_wr = ptr_wr + 1;

    if((~o_empty) && (ptr_rd == ADDR - 2) && (i_rd_en))
        n_ptr_rd = 0;
    else if((~o_empty) && (i_rd_en)) 
        n_ptr_rd = ptr_rd + 1;
end

always @(posedge i_clk or negedge i_rst_n) begin
    if(~i_rst_n) begin
        ptr_rd <= 0;
        ptr_wr <= 0;
    end else begin
        ptr_wr <= n_ptr_wr;
        ptr_rd <= n_ptr_rd; 
    end
end 
endmodule

01_test/tb_fifo.v
`timescale 1ps/1ps
module tb_fifo();

  // Parameters
  parameter DATA_WIDTH = 8;
  parameter SIZE_DEPTH = 8;
  parameter ADDR_WIDTH = $clog2(SIZE_DEPTH);

  // Signals
  reg i_clk, i_rst_n;
  reg i_wr_en; // Changed to reg to drive in initial block
  reg i_rd_en; // Changed to reg to drive in initial block
  reg [DATA_WIDTH-1:0] i_data;
  reg [DATA_WIDTH-1:0] o_data;
  reg o_full, o_empty;
  reg [ADDR_WIDTH-1:0] pt_wr, pt_rd; // FIFO internal pointers (assumed in FIFO module)

  // Memory to store write and read data
  reg [DATA_WIDTH-1:0] value_wr [0:SIZE_DEPTH-1];
  reg [DATA_WIDTH-1:0] value_rd [0:SIZE_DEPTH-1];
  integer count_wr, count_rd;
  integer match_count;
  // Instantiate the FIFO module

  fifo_synchronous #(
                     .SIZE_DATA(DATA_WIDTH),
                     .SIZE_DEPTH(SIZE_DEPTH)
                   ) uut (
                     .i_clk(i_clk),
                     .i_rst_n(i_rst_n),
                     .i_wr_en(i_wr_en),
                     .i_rd_en(i_rd_en),
                     .i_data(i_data),
                     .o_data(o_data),
                     .o_full(o_full),
                     .o_empty(o_empty)
                   );

always #5 i_clk = ~i_clk;

  // Dump waveform
  initial
  begin
    $dumpfile("tb_fifo.vcd");
    $dumpvars(0, tb_fifo);
  end

  // Test procedure
  initial
  begin
    // Initialize signals
    i_rst_n = 0;
    i_wr_en = 0;
    i_rd_en = 0;
    i_data = 0;
    count_wr = 0;
    count_rd = 0;

    // Test case 1: Reset the FIFO
    $display("-------------- Test Case 1 --------------");
    #10;
    i_rst_n = 0;
    @(posedge i_clk);
    i_wr_en = 1;
    i_rd_en = 0;
    i_data = 8'h29;
    #10;

    i_rst_n = 1;
    @(posedge i_clk);
    i_wr_en = 0;
    i_rd_en = 1;
    $display("Test case 1: Reset the FIFO");
    $display("FIFO reset, pt_rd: %d, pt_wr: %d", pt_rd, pt_wr);
    $display("FIFO empty: %d, FIFO full: %d", o_empty, o_full);
    $display("FIFO data: %h", o_data);
    $display("=> TestCase1: %s", (o_data == 8'h00) ? "PASS" : "FAIL");

    // Test case 2: Write data until full
    $display("-------------- Test Case 2 --------------");
    i_rst_n = 0;
    #10;
    i_rst_n = 1;
    count_wr = 0;

    repeat (SIZE_DEPTH + 1)
    begin
      @(posedge i_clk);
      i_wr_en = 1;
      i_rd_en = 0;
      i_data = $random;
      #10;
    end
    i_wr_en = 0;

    $display("Test case 2: Write data until full");
    $display("=> TestCase2: %s", o_full ? "PASS" : "FAIL");

    // Test case 3: Read data until empty
    $display("-------------- Test Case 3 --------------");
    count_rd = 0;
    repeat (SIZE_DEPTH)
    begin
      @(posedge i_clk);
      i_wr_en = 0;
      i_rd_en = 1;
      #10;
      value_rd[count_rd] = o_data;
      count_rd = count_rd + 1;
    end
    i_rd_en = 0;

    $display("Test case 3: Read data until empty");
    $display("=> TestCase3: %s", o_empty ? "PASS" : "FAIL");

    // Test case 4: Write and read simultaneously
    // Kiem tra; doc va ghi dong thoi
    $display("-------------- Test Case 4 --------------");
    #20; // reset 
    i_rst_n = 0;
    
    #20; 
    i_rst_n = 1;
    #10;

    @(posedge i_clk);
    i_wr_en = 1;
    i_rd_en = 0;
    i_data = 29;
    $display("FIFO data: i_data = %d, o_data = %d",i_data, o_data);

    @(posedge i_clk);
    i_wr_en = 1;
    i_rd_en = 1;
    i_data  = 30;
    $display("FIFO data: i_data = %d, o_data = %d",i_data, o_data);

    @(posedge i_clk);
    i_wr_en = 1;
    i_rd_en = 1;
    i_data  = 31;
    $display("FIFO data: i_data = %d, o_data = %d",i_data, o_data);
    
    @(posedge i_clk);
    i_wr_en = 0;
    i_rd_en = 1;
    i_data  = 32;
    $display("FIFO data: i_data = %d, o_data = %d",i_data, o_data);

    @(posedge i_clk);
    i_wr_en = 0;
    i_rd_en = 1;
    i_data  = 33;
    $display("FIFO data: i_data = %d, o_data = %d",i_data, o_data);

    $display("-------------- Test Case 5 --------------");
    // Test case 5: Write data when full

    

    // // Test case 6: Write data when full
    // @(posedge i_clk);
    // i_wr_en = 1;
    // i_rd_en = 0;
    // i_data = $random;
    // #10;
    // i_wr_en = 0;

    // $display("Test case 6: Write data when full");
    // $display("=> TestCase6: %s", o_full ? "PASS" : "FAIL");

    // // Test case 7: Read data when empty
    // i_rst_n = 0;
    // #10;
    // i_rst_n = 1;
    // @(posedge i_clk);
    // i_wr_en = 0;
    // i_rd_en = 1;
    // #10;
    // i_rd_en = 0;

    // $display("Test case 7: Read data when empty");
    // $display("=> TestCase7: %s", o_empty ? "PASS" : "FAIL");

    // End simulation
    #200;
    $display("End of simulation");
    $finish;
  end

endmodule




// `timescale 1ns/1ps
// module tb_fifo();

// reg           clk;
// reg           rst_n;
// reg           i_wr_en;
// reg           i_rd_en;
// reg  [15:0]   i_data;     // Giả định SIZE_DATA = 16
// wire [15:0]   o_data;
// wire          o_full;
// wire          o_empty;

// reg  [15:0]   rdata;
// reg           stop;

// // Instantiate DUT
// fifo_synchronous #(
//   .SIZE_DEPTH(8),
//   .SIZE_DATA(16)
// ) u_fifo (
//   .i_clk     (clk),
//   .i_rst_n   (rst_n),
//   .i_wr_en   (i_wr_en),
//   .i_rd_en   (i_rd_en),
//   .i_data    (i_data),
//   .o_data    (o_data),
//   .o_full    (o_full),
//   .o_empty   (o_empty)
// );

// // Clock generation
// always #10 clk = ~clk;

//   initial
//   begin
//     $dumpfile("tb_fifo.vcd");
//     $dumpvars(0, tb_fifo);
//   end
// // Reset and stimulus init
// initial begin
//   clk      = 0;
//   rst_n    = 0;
//   i_wr_en  = 0;
//   i_rd_en  = 0;
//   stop     = 0;
//   i_data   = 0;

//   #50 rst_n = 1;
// end

// // Write process
// initial begin
//   @(posedge clk);

//   for (int i = 0; i < 20; i++) begin
//     // Wait until FIFO has space
//     while (o_full) begin
//       @(posedge clk);
//       $display("[%0t] FIFO FULL, waiting...", $time);
//     end

//     i_wr_en <= $random;
//     i_data  <= $random;

//     $display("[%0t] WRITE: i=%0d wr_en=%0d data=0x%0h", $time, i, i_wr_en, i_data);
//     @(posedge clk);
//   end

//   i_wr_en <= 0;
//   stop <= 1;
// end

// // Read process
// initial begin
//   @(posedge clk);

//   while (!stop) begin
//     while (o_empty) begin
//       i_rd_en <= 0;
//       $display("[%0t] FIFO EMPTY, waiting...", $time);
//       @(posedge clk);
//     end

//     i_rd_en <= $random;
//     @(posedge clk);
//     rdata <= o_data;
//     $display("[%0t] READ: rd_en=%0d data=0x%0h", $time, i_rd_en, rdata);
//   end

//   i_rd_en <= 0;
//   #500 $finish;
// end

// endmodule

01_test/tb_fifo.vcd
$version Generated by VerilatedVcd $end
$timescale 1ps $end
 $scope module TOP $end
  $scope module tb_fifo $end
   $var wire 32 < DATA_WIDTH [31:0] $end
   $var wire 32 < SIZE_DEPTH [31:0] $end
   $var wire 32 = ADDR_WIDTH [31:0] $end
   $var wire 1 8 i_clk $end
   $var wire 1 # i_rst_n $end
   $var wire 1 $ i_wr_en $end
   $var wire 1 % i_rd_en $end
   $var wire 8 & i_data [7:0] $end
   $var wire 8 1 o_data [7:0] $end
   $var wire 1 9 o_full $end
   $var wire 1 2 o_empty $end
   $var wire 3 > pt_wr [2:0] $end
   $var wire 3 ? pt_rd [2:0] $end
   $var wire 8 @ value_wr[0] [7:0] $end
   $var wire 8 A value_wr[1] [7:0] $end
   $var wire 8 B value_wr[2] [7:0] $end
   $var wire 8 C value_wr[3] [7:0] $end
   $var wire 8 D value_wr[4] [7:0] $end
   $var wire 8 E value_wr[5] [7:0] $end
   $var wire 8 F value_wr[6] [7:0] $end
   $var wire 8 G value_wr[7] [7:0] $end
   $var wire 8 ' value_rd[0] [7:0] $end
   $var wire 8 ( value_rd[1] [7:0] $end
   $var wire 8 ) value_rd[2] [7:0] $end
   $var wire 8 * value_rd[3] [7:0] $end
   $var wire 8 + value_rd[4] [7:0] $end
   $var wire 8 , value_rd[5] [7:0] $end
   $var wire 8 - value_rd[6] [7:0] $end
   $var wire 8 . value_rd[7] [7:0] $end
   $var wire 32 / count_wr [31:0] $end
   $var wire 32 0 count_rd [31:0] $end
   $var wire 32 H match_count [31:0] $end
   $scope module uut $end
    $var wire 32 < SIZE_DEPTH [31:0] $end
    $var wire 32 < SIZE_DATA [31:0] $end
    $var wire 1 8 i_clk $end
    $var wire 1 # i_rst_n $end
    $var wire 1 $ i_wr_en $end
    $var wire 1 % i_rd_en $end
    $var wire 8 & i_data [7:0] $end
    $var wire 8 1 o_data [7:0] $end
    $var wire 1 9 o_full $end
    $var wire 1 2 o_empty $end
    $var wire 32 = ADDR [31:0] $end
    $var wire 3 3 ptr_rd [2:0] $end
    $var wire 3 4 ptr_wr [2:0] $end
    $var wire 3 : n_ptr_rd [2:0] $end
    $var wire 3 ; n_ptr_wr [2:0] $end
    $scope module lut_mem $end
     $var wire 32 < SIZE_DATA [31:0] $end
     $var wire 32 = SIZE_ADDR [31:0] $end
     $var wire 1 8 i_clk $end
     $var wire 1 # i_rst_n $end
     $var wire 1 $ i_wr_en $end
     $var wire 1 % i_rd_en $end
     $var wire 3 4 i_wr_addr [2:0] $end
     $var wire 3 3 i_rd_addr [2:0] $end
     $var wire 8 & i_data [7:0] $end
     $var wire 8 1 o_data [7:0] $end
     $var wire 8 5 mem[0] [7:0] $end
     $var wire 8 6 mem[1] [7:0] $end
     $var wire 8 7 mem[2] [7:0] $end
    $upscope $end
   $upscope $end
  $upscope $end
 $upscope $end
$enddefinitions $end


#0
0#
0$
0%
b00000000 &
b00000000 '
b00000000 (
b00000000 )
b00000000 *
b00000000 +
b00000000 ,
b00000000 -
b00000000 .
b00000000000000000000000000000000 /
b00000000000000000000000000000000 0
b00000000 1
12
b000 3
b000 4
b00000000 5
b00000000 6
b00000000 7
08
19
b000 :
b000 ;
b00000000000000000000000000001000 <
b00000000000000000000000000000011 =
b000 >
b000 ?
b00000000 @
b00000000 A
b00000000 B
b00000000 C
b00000000 D
b00000000 E
b00000000 F
b00000000 G
b00000000000000000000000000000000 H
#5
18
#10
08
#15
1$
b00101001 &
18
#20
08
#25
1#
b00101001 5
18
#30
08
#35
0#
0$
1%
b00000000 5
18
#40
08
#45
1#
18
#50
08
#55
1$
0%
b11000100 &
b11000100 5
18
#60
08
#65
18
#70
08
#75
b10011100 &
b10011100 5
18
#80
08
#85
18
#90
08
#95
b00000010 &
b00000010 5
18
#100
08
#105
18
#110
08
#115
b11100100 &
b11100100 5
18
#120
08
#125
18
#130
08
#135
b01111000 &
b01111000 5
18
#140
08
#145
18
#150
08
#155
b10111100 &
b10111100 5
18
#160
08
#165
18
#170
08
#175
b10110110 &
b10110110 5
18
#180
08
#185
18
#190
08
#195
b11100100 &
b11100100 5
18
#200
08
#205
18
#210
08
#215
b10110111 &
b10110111 5
18
#220
08
#225
0$
18
#230
08
#235
1%
b10110111 1
18
#240
08
#245
b10110111 '
b00000000000000000000000000000001 0
18
#250
08
#255
18
#260
08
#265
b10110111 (
b00000000000000000000000000000010 0
18
#270
08
#275
18
#280
08
#285
b10110111 )
b00000000000000000000000000000011 0
18
#290
08
#295
18
#300
08
#305
b10110111 *
b00000000000000000000000000000100 0
18
#310
08
#315
18
#320
08
#325
b10110111 +
b00000000000000000000000000000101 0
18
#330
08
#335
18
#340
08
#345
b10110111 ,
b00000000000000000000000000000110 0
18
#350
08
#355
18
#360
08
#365
b10110111 -
b00000000000000000000000000000111 0
18
#370
08
#375
18
#380
08
#385
0%
b10110111 .
b00000000000000000000000000001000 0
18
#390
08
#395
18
#400
08
#405
0#
b00000000 1
b00000000 5
18
#410
08
#415
18
#420
08
#425
1#
18
#430
08
#435
18
#440
08
#445
1$
b00011101 &
b00011101 5
18
#450
08
#455
1%
b00011110 &
b00011110 5
18
#460
08
#465
b00011111 &
b00011111 5
18
#470
08
#475
0$
b00100000 &
b00011111 1
18
#480
08
#485
b00100001 &
18
